examples/__init__.py
examples/create-and-validate.py
examples/web.py
examples/google/__init__.py
examples/google/app.py
oatk/__init__.py
oatk/__main__.py
oatk/fake/__init__.py
oatk/fake/db.py
oatk/fake/routes.py
oatk/fake/static/__init__.py
oatk/fake/static/oatk.js
oatk/fake/static/style.css
oatk/fake/templates/__init__.py
oatk/fake/templates/authorize.html
oatk/fake/templates/base.html
oatk/fake/templates/create_client.html
oatk/fake/templates/dialog.html
oatk/fake/templates/home.html
oatk/fake/templates/login.html
oatk/js/__init__.py
oatk/js/oatk.js
oatk/js/__pycache__/__init__.cpython-311.pyc
oatk/js/__pycache__/__init__.cpython-38.pyc
oatk-0.1.5.dist-info/licenses/LICENSE.txt
oatk-0.1.5.dist-info/METADATA
oatk-0.1.5.dist-info/WHEEL
oatk-0.1.5.dist-info/entry_points.txt
oatk-0.1.5.dist-info/top_level.txt
oatk-0.1.5.dist-info/RECORD
