Metadata-Version: 2.4
Name: oatk
Version: 0.1.5
Summary: A collection of useful functions for dealing with OAuth
Home-page: https://github.com/christophevg/oatk
Author: Christophe VG
License: MIT
Keywords: oauth human
Classifier: Topic :: Security :: Cryptography
Classifier: Programming Language :: Python :: 3
Classifier: Programming Language :: Python :: 3.8
Classifier: Development Status :: 4 - Beta
License-File: LICENSE.txt
Requires-Dist: pyjwt
Requires-Dist: cryptography
Requires-Dist: python-dotenv
Requires-Dist: fire
Requires-Dist: authlib
Requires-Dist: flask
Requires-Dist: flask_cors
Requires-Dist: flask_restful
Requires-Dist: pymongo
Requires-Dist: requests
Dynamic: author
Dynamic: classifier
Dynamic: description
Dynamic: description-content-type
Dynamic: home-page
Dynamic: keywords
Dynamic: license
Dynamic: license-file
Dynamic: requires-dist
Dynamic: summary
